hollerithmltraintrack/__init__.py
hollerithmltraintrack/csv_exporter.py
hollerithmltraintrack/energy_tracker.py
hollerithmltraintrack/main.py
hollerithmltraintrack/model_tracking.py
tests/__init__.py
tests/test_main.py
HollerithMLTrainTrack-0.1.0.dist-info/LICENSE
HollerithMLTrainTrack-0.1.0.dist-info/METADATA
HollerithMLTrainTrack-0.1.0.dist-info/WHEEL
HollerithMLTrainTrack-0.1.0.dist-info/top_level.txt
HollerithMLTrainTrack-0.1.0.dist-info/RECORD
