Metadata-Version: 2.1
Name: HollerithMLTrainTrack
Version: 0.1.0
Summary: A tool for tracking and analyzing ML model training processes.
Home-page: https://github.com/lukasgro63/hollerithmltraintrack
Author: Lukas Grodmeier
Author-email: lukasgro63@gmail.com
Classifier: Development Status :: 3 - Alpha
Classifier: Programming Language :: Python :: 3
Classifier: License :: OSI Approved :: MIT License
Classifier: Operating System :: OS Independent
Requires-Python: >=3.6
License-File: LICENSE
Requires-Dist: scikit-learn
Requires-Dist: pandas
Requires-Dist: numpy
Requires-Dist: codecarbon
Provides-Extra: dev
Requires-Dist: pytest ; extra == 'dev'
Requires-Dist: flake8 ; extra == 'dev'
